pymaxed/__init__.py
pymaxed/lagrangian.py
pymaxed/maxed.py
pymaxed/minimize.py
pymaxed/pdfs.py
pymaxed/tools.py
pymaxed/vectors.py
pymaxed-0.1.7.dist-info/WHEEL
pymaxed-0.1.7.dist-info/METADATA
pymaxed-0.1.7.dist-info/RECORD
